ValLib/__init__.py
ValLib/api.py
ValLib/debug.py
ValLib/exceptions.py
ValLib/parsing.py
ValLib/request.py
ValLib/structs.py
ValLib/version.py
ValLib/auth/__init__.py
ValLib/auth/auth.py
ValLib/auth/captcha.py
ValLib/auth/context.py
ValLib/auth/helper.py
ValLib/auth/info.py
ValLib/auth/mfa.py
ValLib/auth/setup.py
ValLib/auth/token.py
ValLib/auth/validation.py
ValLib/auth/legacy/__init__.py
ValLib/auth/legacy/login.py
ValLib/auth/legacy/mfa.py
ValLib/captcha/__init__.py
ValLib/captcha/alternative.py
ValLib/captcha/exceptions.py
ValLib/captcha/handler.py
ValLib/captcha/http.py
ValLib/captcha/port.py
ValLib/captcha/struct.py
ValLib/captcha/web.py
ValLib/captcha/assets/captcha.html
ValLib/mfa/__init__.py
ValLib/mfa/alternative.py
ValLib/mfa/default.py
ValLib/mfa/struct.py
ValLib-1.5.0.dist-info/LICENSE
ValLib-1.5.0.dist-info/METADATA
ValLib-1.5.0.dist-info/WHEEL
ValLib-1.5.0.dist-info/top_level.txt
ValLib-1.5.0.dist-info/RECORD
