Metadata-Version: 2.1
Name: ValLib
Version: 1.5.0
Author: PWall
License: GPL-3.0
Project-URL: Homepage, https://github.com/ValUtils/ValLib
Keywords: valorant,api,auth
Requires-Python: >=3.8
License-File: LICENSE
Requires-Dist: importlib-resources
Requires-Dist: httpx
Requires-Dist: pyjwt
